AuPyL/BUTTON.py
AuPyL/CLEAR.py
AuPyL/CONTROL.py
AuPyL/ERR.py
AuPyL/HOOK_ERR.py
AuPyL/PUTTEXT.py
AuPyL/SCREEN.py
AuPyL/SHOWIMG.py
AuPyL/__init__.py
AuPyL/_import_module.py
AuPyL/urlOpen.py
AuPyL-0.2.dist-info/METADATA
AuPyL-0.2.dist-info/WHEEL
AuPyL-0.2.dist-info/top_level.txt
AuPyL-0.2.dist-info/RECORD
