Metadata-Version: 2.1
Name: AuPyL
Version: 0.2
Summary: AutoPy Lite For Termux
Author: None
Author-email: NoneAndNone@No.com
Requires-Python: >=3.9
